mySelfSumHy.py
mySelfSumHy-1.2.dist-info/METADATA
mySelfSumHy-1.2.dist-info/WHEEL
mySelfSumHy-1.2.dist-info/top_level.txt
mySelfSumHy-1.2.dist-info/RECORD
