Metadata-Version: 2.1
Name: mySelfSumHy
Version: 1.2
Summary: A  module for test
Home-page: https://github.com/vfrtgb158/email
Author: houyan
Author-email: houyan@qiyi.com
License: MIT
Platform: UNKNOWN
